<?xml version="1.0" ?>
  <Gesture Name="x06" Subject="Jewel P" Speed="medium" Number="6" NumPts="39" AppName="dollarstore-notepad" Date="2022-02-17" Time="14:29:33.758781">
    <Point X="171.0" Y="203.0" T="14:29:33.758827"/>
    <Point X="172.0" Y="204.0" T="14:29:33.758861"/>
    <Point X="185.0" Y="214.0" T="14:29:33.759096"/>
    <Point X="206.0" Y="235.0" T="14:29:33.759132"/>
    <Point X="236.0" Y="267.0" T="14:29:33.759164"/>
    <Point X="255.0" Y="285.0" T="14:29:33.759196"/>
    <Point X="269.0" Y="300.0" T="14:29:33.759228"/>
    <Point X="277.0" Y="307.0" T="14:29:33.759260"/>
    <Point X="282.0" Y="311.0" T="14:29:33.759291"/>
    <Point X="283.0" Y="312.0" T="14:29:33.759323"/>
    <Point X="283.0" Y="311.0" T="14:29:33.759367"/>
    <Point X="283.0" Y="306.0" T="14:29:33.759498"/>
    <Point X="283.0" Y="298.0" T="14:29:33.759543"/>
    <Point X="283.0" Y="281.0" T="14:29:33.759580"/>
    <Point X="283.0" Y="263.0" T="14:29:33.759619"/>
    <Point X="282.0" Y="253.0" T="14:29:33.759651"/>
    <Point X="279.0" Y="237.0" T="14:29:33.759683"/>
    <Point X="274.0" Y="216.0" T="14:29:33.759716"/>
    <Point X="270.0" Y="200.0" T="14:29:33.759749"/>
    <Point X="267.0" Y="191.0" T="14:29:33.759781"/>
    <Point X="265.0" Y="183.0" T="14:29:33.759813"/>
    <Point X="264.0" Y="179.0" T="14:29:33.759844"/>
    <Point X="263.0" Y="177.0" T="14:29:33.759876"/>
    <Point X="262.0" Y="178.0" T="14:29:33.759910"/>
    <Point X="261.0" Y="180.0" T="14:29:33.759941"/>
    <Point X="258.0" Y="184.0" T="14:29:33.759973"/>
    <Point X="249.0" Y="194.0" T="14:29:33.760004"/>
    <Point X="235.0" Y="210.0" T="14:29:33.760035"/>
    <Point X="215.0" Y="232.0" T="14:29:33.760066"/>
    <Point X="194.0" Y="254.0" T="14:29:33.760096"/>
    <Point X="179.0" Y="269.0" T="14:29:33.760127"/>
    <Point X="164.0" Y="284.0" T="14:29:33.760158"/>
    <Point X="153.0" Y="294.0" T="14:29:33.760190"/>
    <Point X="147.0" Y="299.0" T="14:29:33.760222"/>
    <Point X="143.0" Y="303.0" T="14:29:33.760254"/>
    <Point X="140.0" Y="305.0" T="14:29:33.760286"/>
    <Point X="138.0" Y="306.0" T="14:29:33.760318"/>
    <Point X="138.0" Y="307.0" T="14:29:33.760349"/>
    <Point X="137.0" Y="307.0" T="14:29:33.760381"/>
  </Gesture>
