<?xml version="1.0" ?>
  <Gesture Name="caret10" Subject="Drew B" Speed="medium" Number="10" NumPts="22" AppName="dollarstore-notepad" Date="2022-02-17" Time="15:23:37.892715">
    <Point X="267.0" Y="331.0" T="15:23:37.892813"/>
    <Point X="267.0" Y="330.0" T="15:23:37.892888"/>
    <Point X="272.0" Y="320.0" T="15:23:37.892970"/>
    <Point X="279.0" Y="307.0" T="15:23:37.893043"/>
    <Point X="289.0" Y="291.0" T="15:23:37.893114"/>
    <Point X="296.0" Y="279.0" T="15:23:37.893184"/>
    <Point X="305.0" Y="267.0" T="15:23:37.893256"/>
    <Point X="309.0" Y="260.0" T="15:23:37.893695"/>
    <Point X="311.0" Y="257.0" T="15:23:37.893767"/>
    <Point X="314.0" Y="253.0" T="15:23:37.893855"/>
    <Point X="316.0" Y="253.0" T="15:23:37.893926"/>
    <Point X="317.0" Y="253.0" T="15:23:37.894019"/>
    <Point X="317.0" Y="254.0" T="15:23:37.894068"/>
    <Point X="317.0" Y="256.0" T="15:23:37.894114"/>
    <Point X="317.0" Y="261.0" T="15:23:37.894160"/>
    <Point X="317.0" Y="270.0" T="15:23:37.894205"/>
    <Point X="317.0" Y="283.0" T="15:23:37.894251"/>
    <Point X="323.0" Y="315.0" T="15:23:37.894304"/>
    <Point X="326.0" Y="331.0" T="15:23:37.894351"/>
    <Point X="328.0" Y="339.0" T="15:23:37.894397"/>
    <Point X="330.0" Y="345.0" T="15:23:37.894442"/>
    <Point X="331.0" Y="348.0" T="15:23:37.894489"/>
  </Gesture>
