<?xml version="1.0" ?>
  <Gesture Name="check03" Subject="S01" Speed="medium" Number="3" NumPts="59" AppName="dollarstore-notepad" Date="2022-02-17" Time="16:25:59.249921">
    <Point X="74.0" Y="232.0" T="16:25:59.249974"/>
    <Point X="75.0" Y="232.0" T="16:25:59.250013"/>
    <Point X="76.0" Y="235.0" T="16:25:59.250044"/>
    <Point X="81.0" Y="243.0" T="16:25:59.250074"/>
    <Point X="86.0" Y="251.0" T="16:25:59.250104"/>
    <Point X="92.0" Y="258.0" T="16:25:59.250133"/>
    <Point X="104.0" Y="275.0" T="16:25:59.250162"/>
    <Point X="109.0" Y="281.0" T="16:25:59.250192"/>
    <Point X="128.0" Y="306.0" T="16:25:59.250221"/>
    <Point X="131.0" Y="310.0" T="16:25:59.250343"/>
    <Point X="136.0" Y="315.0" T="16:25:59.250374"/>
    <Point X="137.0" Y="317.0" T="16:25:59.250404"/>
    <Point X="137.0" Y="318.0" T="16:25:59.250433"/>
    <Point X="138.0" Y="319.0" T="16:25:59.250462"/>
    <Point X="139.0" Y="321.0" T="16:25:59.250492"/>
    <Point X="142.0" Y="326.0" T="16:25:59.250521"/>
    <Point X="142.0" Y="327.0" T="16:25:59.250550"/>
    <Point X="144.0" Y="329.0" T="16:25:59.250579"/>
    <Point X="146.0" Y="333.0" T="16:25:59.250609"/>
    <Point X="147.0" Y="334.0" T="16:25:59.250638"/>
    <Point X="148.0" Y="335.0" T="16:25:59.250667"/>
    <Point X="149.0" Y="337.0" T="16:25:59.250697"/>
    <Point X="150.0" Y="339.0" T="16:25:59.250726"/>
    <Point X="152.0" Y="342.0" T="16:25:59.250756"/>
    <Point X="153.0" Y="344.0" T="16:25:59.250785"/>
    <Point X="154.0" Y="345.0" T="16:25:59.250815"/>
    <Point X="154.0" Y="345.0" T="16:25:59.250845"/>
    <Point X="154.0" Y="343.0" T="16:25:59.250875"/>
    <Point X="156.0" Y="340.0" T="16:25:59.250904"/>
    <Point X="165.0" Y="325.0" T="16:25:59.250933"/>
    <Point X="174.0" Y="309.0" T="16:25:59.250963"/>
    <Point X="192.0" Y="284.0" T="16:25:59.250992"/>
    <Point X="209.0" Y="260.0" T="16:25:59.251022"/>
    <Point X="227.0" Y="234.0" T="16:25:59.251051"/>
    <Point X="244.0" Y="211.0" T="16:25:59.251081"/>
    <Point X="262.0" Y="189.0" T="16:25:59.251110"/>
    <Point X="278.0" Y="167.0" T="16:25:59.251139"/>
    <Point X="299.0" Y="140.0" T="16:25:59.251168"/>
    <Point X="306.0" Y="130.0" T="16:25:59.251267"/>
    <Point X="320.0" Y="114.0" T="16:25:59.251307"/>
    <Point X="337.0" Y="95.0" T="16:25:59.251339"/>
    <Point X="346.0" Y="86.0" T="16:25:59.251370"/>
    <Point X="353.0" Y="80.0" T="16:25:59.251400"/>
    <Point X="357.0" Y="76.0" T="16:25:59.251430"/>
    <Point X="362.0" Y="72.0" T="16:25:59.251460"/>
    <Point X="366.0" Y="68.0" T="16:25:59.251490"/>
    <Point X="369.0" Y="66.0" T="16:25:59.251519"/>
    <Point X="371.0" Y="64.0" T="16:25:59.251549"/>
    <Point X="374.0" Y="62.0" T="16:25:59.251579"/>
    <Point X="378.0" Y="59.0" T="16:25:59.251608"/>
    <Point X="382.0" Y="57.0" T="16:25:59.251638"/>
    <Point X="383.0" Y="56.0" T="16:25:59.251667"/>
    <Point X="387.0" Y="53.0" T="16:25:59.251697"/>
    <Point X="390.0" Y="51.0" T="16:25:59.251727"/>
    <Point X="390.0" Y="50.0" T="16:25:59.251757"/>
    <Point X="392.0" Y="49.0" T="16:25:59.251787"/>
    <Point X="393.0" Y="48.0" T="16:25:59.251817"/>
    <Point X="393.0" Y="47.0" T="16:25:59.251847"/>
    <Point X="394.0" Y="47.0" T="16:25:59.251876"/>
  </Gesture>
