<?xml version="1.0" ?>
  <Gesture Name="delete_mark01" Subject="S01" Speed="medium" Number="1" NumPts="111" AppName="dollarstore-notepad" Date="2022-02-17" Time="16:26:48.195397">
    <Point X="116.0" Y="63.0" T="16:26:48.195437"/>
    <Point X="115.0" Y="63.0" T="16:26:48.195469"/>
    <Point X="116.0" Y="65.0" T="16:26:48.195499"/>
    <Point X="118.0" Y="69.0" T="16:26:48.195528"/>
    <Point X="127.0" Y="82.0" T="16:26:48.195557"/>
    <Point X="129.0" Y="86.0" T="16:26:48.195587"/>
    <Point X="138.0" Y="100.0" T="16:26:48.195623"/>
    <Point X="145.0" Y="110.0" T="16:26:48.195657"/>
    <Point X="151.0" Y="118.0" T="16:26:48.195698"/>
    <Point X="156.0" Y="124.0" T="16:26:48.195730"/>
    <Point X="163.0" Y="132.0" T="16:26:48.195759"/>
    <Point X="171.0" Y="140.0" T="16:26:48.195789"/>
    <Point X="173.0" Y="142.0" T="16:26:48.195819"/>
    <Point X="176.0" Y="147.0" T="16:26:48.195849"/>
    <Point X="183.0" Y="154.0" T="16:26:48.195879"/>
    <Point X="188.0" Y="160.0" T="16:26:48.195909"/>
    <Point X="193.0" Y="166.0" T="16:26:48.195938"/>
    <Point X="198.0" Y="171.0" T="16:26:48.195968"/>
    <Point X="205.0" Y="178.0" T="16:26:48.195998"/>
    <Point X="226.0" Y="196.0" T="16:26:48.196027"/>
    <Point X="248.0" Y="216.0" T="16:26:48.196057"/>
    <Point X="252.0" Y="220.0" T="16:26:48.196086"/>
    <Point X="259.0" Y="226.0" T="16:26:48.196116"/>
    <Point X="268.0" Y="235.0" T="16:26:48.196145"/>
    <Point X="287.0" Y="253.0" T="16:26:48.196174"/>
    <Point X="298.0" Y="261.0" T="16:26:48.196204"/>
    <Point X="303.0" Y="266.0" T="16:26:48.196234"/>
    <Point X="316.0" Y="278.0" T="16:26:48.196264"/>
    <Point X="323.0" Y="285.0" T="16:26:48.196293"/>
    <Point X="329.0" Y="293.0" T="16:26:48.196322"/>
    <Point X="337.0" Y="299.0" T="16:26:48.196351"/>
    <Point X="345.0" Y="308.0" T="16:26:48.196381"/>
    <Point X="353.0" Y="315.0" T="16:26:48.196411"/>
    <Point X="359.0" Y="320.0" T="16:26:48.196441"/>
    <Point X="363.0" Y="324.0" T="16:26:48.196471"/>
    <Point X="364.0" Y="324.0" T="16:26:48.196501"/>
    <Point X="366.0" Y="327.0" T="16:26:48.196531"/>
    <Point X="367.0" Y="328.0" T="16:26:48.196561"/>
    <Point X="369.0" Y="331.0" T="16:26:48.196591"/>
    <Point X="370.0" Y="333.0" T="16:26:48.196621"/>
    <Point X="373.0" Y="336.0" T="16:26:48.196727"/>
    <Point X="374.0" Y="339.0" T="16:26:48.196758"/>
    <Point X="375.0" Y="341.0" T="16:26:48.196788"/>
    <Point X="376.0" Y="341.0" T="16:26:48.196818"/>
    <Point X="376.0" Y="342.0" T="16:26:48.196848"/>
    <Point X="373.0" Y="342.0" T="16:26:48.196894"/>
    <Point X="371.0" Y="342.0" T="16:26:48.196945"/>
    <Point X="366.0" Y="343.0" T="16:26:48.196977"/>
    <Point X="350.0" Y="347.0" T="16:26:48.197007"/>
    <Point X="326.0" Y="350.0" T="16:26:48.197036"/>
    <Point X="299.0" Y="352.0" T="16:26:48.197067"/>
    <Point X="271.0" Y="353.0" T="16:26:48.197096"/>
    <Point X="266.0" Y="353.0" T="16:26:48.197126"/>
    <Point X="257.0" Y="353.0" T="16:26:48.197156"/>
    <Point X="245.0" Y="352.0" T="16:26:48.197186"/>
    <Point X="230.0" Y="352.0" T="16:26:48.197215"/>
    <Point X="210.0" Y="350.0" T="16:26:48.197245"/>
    <Point X="197.0" Y="350.0" T="16:26:48.197275"/>
    <Point X="186.0" Y="350.0" T="16:26:48.197305"/>
    <Point X="177.0" Y="350.0" T="16:26:48.197335"/>
    <Point X="170.0" Y="351.0" T="16:26:48.197364"/>
    <Point X="165.0" Y="351.0" T="16:26:48.197394"/>
    <Point X="161.0" Y="351.0" T="16:26:48.197423"/>
    <Point X="151.0" Y="352.0" T="16:26:48.197453"/>
    <Point X="145.0" Y="352.0" T="16:26:48.197482"/>
    <Point X="131.0" Y="353.0" T="16:26:48.197513"/>
    <Point X="114.0" Y="354.0" T="16:26:48.197542"/>
    <Point X="113.0" Y="354.0" T="16:26:48.197572"/>
    <Point X="112.0" Y="354.0" T="16:26:48.197601"/>
    <Point X="111.0" Y="354.0" T="16:26:48.197631"/>
    <Point X="110.0" Y="355.0" T="16:26:48.197661"/>
    <Point X="109.0" Y="355.0" T="16:26:48.197690"/>
    <Point X="109.0" Y="354.0" T="16:26:48.197720"/>
    <Point X="109.0" Y="350.0" T="16:26:48.197749"/>
    <Point X="112.0" Y="342.0" T="16:26:48.197779"/>
    <Point X="115.0" Y="333.0" T="16:26:48.197808"/>
    <Point X="115.0" Y="329.0" T="16:26:48.197838"/>
    <Point X="122.0" Y="313.0" T="16:26:48.197869"/>
    <Point X="128.0" Y="302.0" T="16:26:48.197899"/>
    <Point X="137.0" Y="286.0" T="16:26:48.197928"/>
    <Point X="147.0" Y="272.0" T="16:26:48.197958"/>
    <Point X="156.0" Y="255.0" T="16:26:48.197988"/>
    <Point X="164.0" Y="242.0" T="16:26:48.198017"/>
    <Point X="178.0" Y="221.0" T="16:26:48.198047"/>
    <Point X="182.0" Y="215.0" T="16:26:48.198081"/>
    <Point X="196.0" Y="194.0" T="16:26:48.198116"/>
    <Point X="203.0" Y="185.0" T="16:26:48.198146"/>
    <Point X="205.0" Y="182.0" T="16:26:48.198175"/>
    <Point X="209.0" Y="176.0" T="16:26:48.198204"/>
    <Point X="211.0" Y="173.0" T="16:26:48.198234"/>
    <Point X="213.0" Y="172.0" T="16:26:48.198263"/>
    <Point X="215.0" Y="169.0" T="16:26:48.198292"/>
    <Point X="219.0" Y="166.0" T="16:26:48.198321"/>
    <Point X="224.0" Y="160.0" T="16:26:48.198351"/>
    <Point X="227.0" Y="157.0" T="16:26:48.198449"/>
    <Point X="233.0" Y="151.0" T="16:26:48.198480"/>
    <Point X="237.0" Y="147.0" T="16:26:48.198509"/>
    <Point X="242.0" Y="141.0" T="16:26:48.198539"/>
    <Point X="253.0" Y="131.0" T="16:26:48.198568"/>
    <Point X="258.0" Y="124.0" T="16:26:48.198598"/>
    <Point X="273.0" Y="108.0" T="16:26:48.198627"/>
    <Point X="296.0" Y="85.0" T="16:26:48.198657"/>
    <Point X="306.0" Y="74.0" T="16:26:48.198687"/>
    <Point X="315.0" Y="65.0" T="16:26:48.198716"/>
    <Point X="319.0" Y="61.0" T="16:26:48.198746"/>
    <Point X="322.0" Y="58.0" T="16:26:48.198775"/>
    <Point X="323.0" Y="57.0" T="16:26:48.198805"/>
    <Point X="324.0" Y="57.0" T="16:26:48.198834"/>
    <Point X="324.0" Y="56.0" T="16:26:48.198863"/>
    <Point X="325.0" Y="55.0" T="16:26:48.198895"/>
    <Point X="326.0" Y="54.0" T="16:26:48.198925"/>
  </Gesture>
