<?xml version="1.0" ?>
  <Gesture Name="right_sq_bracket10" Subject="Lindsey R" Speed="medium" Number="10" NumPts="60" AppName="dollarstore-notepad" Date="2022-02-17" Time="15:58:20.546548">
    <Point X="337.0" Y="67.0" T="15:58:20.546674"/>
    <Point X="339.0" Y="67.0" T="15:58:20.546751"/>
    <Point X="351.0" Y="67.0" T="15:58:20.546825"/>
    <Point X="365.0" Y="67.0" T="15:58:20.546895"/>
    <Point X="388.0" Y="67.0" T="15:58:20.546965"/>
    <Point X="402.0" Y="67.0" T="15:58:20.547037"/>
    <Point X="409.0" Y="67.0" T="15:58:20.547108"/>
    <Point X="415.0" Y="67.0" T="15:58:20.547179"/>
    <Point X="419.0" Y="67.0" T="15:58:20.547249"/>
    <Point X="422.0" Y="67.0" T="15:58:20.547321"/>
    <Point X="424.0" Y="68.0" T="15:58:20.547391"/>
    <Point X="425.0" Y="69.0" T="15:58:20.547462"/>
    <Point X="426.0" Y="71.0" T="15:58:20.547561"/>
    <Point X="426.0" Y="76.0" T="15:58:20.547855"/>
    <Point X="427.0" Y="83.0" T="15:58:20.547928"/>
    <Point X="428.0" Y="97.0" T="15:58:20.547999"/>
    <Point X="430.0" Y="113.0" T="15:58:20.548096"/>
    <Point X="431.0" Y="136.0" T="15:58:20.548170"/>
    <Point X="433.0" Y="162.0" T="15:58:20.548257"/>
    <Point X="434.0" Y="188.0" T="15:58:20.548328"/>
    <Point X="435.0" Y="206.0" T="15:58:20.548398"/>
    <Point X="435.0" Y="226.0" T="15:58:20.548487"/>
    <Point X="435.0" Y="243.0" T="15:58:20.548562"/>
    <Point X="435.0" Y="257.0" T="15:58:20.548617"/>
    <Point X="435.0" Y="269.0" T="15:58:20.548668"/>
    <Point X="435.0" Y="280.0" T="15:58:20.548715"/>
    <Point X="433.0" Y="288.0" T="15:58:20.548761"/>
    <Point X="432.0" Y="296.0" T="15:58:20.548808"/>
    <Point X="431.0" Y="304.0" T="15:58:20.548861"/>
    <Point X="431.0" Y="309.0" T="15:58:20.548908"/>
    <Point X="430.0" Y="314.0" T="15:58:20.548959"/>
    <Point X="429.0" Y="318.0" T="15:58:20.549098"/>
    <Point X="429.0" Y="319.0" T="15:58:20.549261"/>
    <Point X="429.0" Y="321.0" T="15:58:20.549352"/>
    <Point X="428.0" Y="322.0" T="15:58:20.549409"/>
    <Point X="426.0" Y="322.0" T="15:58:20.549565"/>
    <Point X="424.0" Y="322.0" T="15:58:20.549640"/>
    <Point X="422.0" Y="322.0" T="15:58:20.549690"/>
    <Point X="420.0" Y="322.0" T="15:58:20.549738"/>
    <Point X="417.0" Y="322.0" T="15:58:20.549813"/>
    <Point X="414.0" Y="322.0" T="15:58:20.549862"/>
    <Point X="411.0" Y="322.0" T="15:58:20.549920"/>
    <Point X="409.0" Y="322.0" T="15:58:20.549967"/>
    <Point X="405.0" Y="321.0" T="15:58:20.550014"/>
    <Point X="400.0" Y="320.0" T="15:58:20.550072"/>
    <Point X="394.0" Y="320.0" T="15:58:20.550130"/>
    <Point X="382.0" Y="319.0" T="15:58:20.550184"/>
    <Point X="372.0" Y="319.0" T="15:58:20.550237"/>
    <Point X="360.0" Y="319.0" T="15:58:20.550284"/>
    <Point X="354.0" Y="319.0" T="15:58:20.550336"/>
    <Point X="348.0" Y="319.0" T="15:58:20.550384"/>
    <Point X="345.0" Y="320.0" T="15:58:20.550431"/>
    <Point X="344.0" Y="321.0" T="15:58:20.550478"/>
    <Point X="342.0" Y="321.0" T="15:58:20.550526"/>
    <Point X="341.0" Y="321.0" T="15:58:20.550574"/>
    <Point X="339.0" Y="321.0" T="15:58:20.550627"/>
    <Point X="337.0" Y="322.0" T="15:58:20.550674"/>
    <Point X="335.0" Y="322.0" T="15:58:20.550833"/>
    <Point X="335.0" Y="323.0" T="15:58:20.550892"/>
    <Point X="333.0" Y="323.0" T="15:58:20.550940"/>
  </Gesture>
