<?xml version="1.0" ?>
  <Gesture Name="left_curly_brace04" Subject="S02" Speed="medium" Number="4" NumPts="75" AppName="dollarstore-notepad" Date="2022-02-17" Time="16:37:35.369252">
    <Point X="257.0" Y="54.0" T="16:37:35.369293"/>
    <Point X="257.0" Y="55.0" T="16:37:35.369324"/>
    <Point X="256.0" Y="55.0" T="16:37:35.369354"/>
    <Point X="255.0" Y="55.0" T="16:37:35.369383"/>
    <Point X="253.0" Y="56.0" T="16:37:35.369412"/>
    <Point X="247.0" Y="57.0" T="16:37:35.369442"/>
    <Point X="235.0" Y="58.0" T="16:37:35.369471"/>
    <Point X="219.0" Y="58.0" T="16:37:35.369501"/>
    <Point X="202.0" Y="58.0" T="16:37:35.369530"/>
    <Point X="187.0" Y="58.0" T="16:37:35.369559"/>
    <Point X="163.0" Y="59.0" T="16:37:35.369588"/>
    <Point X="134.0" Y="62.0" T="16:37:35.369617"/>
    <Point X="110.0" Y="66.0" T="16:37:35.369646"/>
    <Point X="89.0" Y="76.0" T="16:37:35.369674"/>
    <Point X="78.0" Y="84.0" T="16:37:35.369704"/>
    <Point X="73.0" Y="90.0" T="16:37:35.369733"/>
    <Point X="71.0" Y="102.0" T="16:37:35.369762"/>
    <Point X="72.0" Y="114.0" T="16:37:35.369797"/>
    <Point X="79.0" Y="125.0" T="16:37:35.369870"/>
    <Point X="94.0" Y="140.0" T="16:37:35.369937"/>
    <Point X="118.0" Y="155.0" T="16:37:35.370065"/>
    <Point X="133.0" Y="165.0" T="16:37:35.370097"/>
    <Point X="145.0" Y="172.0" T="16:37:35.370126"/>
    <Point X="147.0" Y="173.0" T="16:37:35.370155"/>
    <Point X="147.0" Y="175.0" T="16:37:35.370184"/>
    <Point X="147.0" Y="177.0" T="16:37:35.370214"/>
    <Point X="146.0" Y="178.0" T="16:37:35.370243"/>
    <Point X="146.0" Y="180.0" T="16:37:35.370273"/>
    <Point X="143.0" Y="184.0" T="16:37:35.370302"/>
    <Point X="138.0" Y="187.0" T="16:37:35.370331"/>
    <Point X="133.0" Y="190.0" T="16:37:35.370360"/>
    <Point X="127.0" Y="193.0" T="16:37:35.370389"/>
    <Point X="125.0" Y="194.0" T="16:37:35.370418"/>
    <Point X="123.0" Y="196.0" T="16:37:35.370447"/>
    <Point X="123.0" Y="197.0" T="16:37:35.370476"/>
    <Point X="123.0" Y="200.0" T="16:37:35.370505"/>
    <Point X="123.0" Y="202.0" T="16:37:35.370535"/>
    <Point X="124.0" Y="206.0" T="16:37:35.370564"/>
    <Point X="126.0" Y="209.0" T="16:37:35.370593"/>
    <Point X="130.0" Y="213.0" T="16:37:35.370622"/>
    <Point X="138.0" Y="218.0" T="16:37:35.370651"/>
    <Point X="144.0" Y="223.0" T="16:37:35.370680"/>
    <Point X="147.0" Y="226.0" T="16:37:35.370709"/>
    <Point X="148.0" Y="227.0" T="16:37:35.370738"/>
    <Point X="148.0" Y="229.0" T="16:37:35.370767"/>
    <Point X="147.0" Y="229.0" T="16:37:35.370796"/>
    <Point X="146.0" Y="231.0" T="16:37:35.370825"/>
    <Point X="145.0" Y="232.0" T="16:37:35.370854"/>
    <Point X="138.0" Y="235.0" T="16:37:35.370883"/>
    <Point X="134.0" Y="236.0" T="16:37:35.370912"/>
    <Point X="131.0" Y="238.0" T="16:37:35.370941"/>
    <Point X="128.0" Y="241.0" T="16:37:35.370970"/>
    <Point X="125.0" Y="243.0" T="16:37:35.370998"/>
    <Point X="123.0" Y="245.0" T="16:37:35.371071"/>
    <Point X="122.0" Y="248.0" T="16:37:35.371118"/>
    <Point X="122.0" Y="250.0" T="16:37:35.371150"/>
    <Point X="122.0" Y="252.0" T="16:37:35.371180"/>
    <Point X="122.0" Y="254.0" T="16:37:35.371210"/>
    <Point X="123.0" Y="256.0" T="16:37:35.371241"/>
    <Point X="123.0" Y="258.0" T="16:37:35.371271"/>
    <Point X="125.0" Y="261.0" T="16:37:35.371300"/>
    <Point X="127.0" Y="265.0" T="16:37:35.371330"/>
    <Point X="130.0" Y="268.0" T="16:37:35.371359"/>
    <Point X="134.0" Y="272.0" T="16:37:35.371389"/>
    <Point X="143.0" Y="279.0" T="16:37:35.371419"/>
    <Point X="158.0" Y="285.0" T="16:37:35.371450"/>
    <Point X="174.0" Y="288.0" T="16:37:35.371480"/>
    <Point X="187.0" Y="291.0" T="16:37:35.371509"/>
    <Point X="191.0" Y="291.0" T="16:37:35.371539"/>
    <Point X="209.0" Y="292.0" T="16:37:35.371568"/>
    <Point X="223.0" Y="293.0" T="16:37:35.371598"/>
    <Point X="240.0" Y="294.0" T="16:37:35.371627"/>
    <Point X="250.0" Y="294.0" T="16:37:35.371657"/>
    <Point X="254.0" Y="294.0" T="16:37:35.371686"/>
    <Point X="254.0" Y="293.0" T="16:37:35.371789"/>
  </Gesture>
