<?xml version="1.0" ?>
  <Gesture Name="rectangle01" Subject="S02" Speed="medium" Number="1" NumPts="106" AppName="dollarstore-notepad" Date="2022-02-17" Time="16:39:02.203253">
    <Point X="81.0" Y="144.0" T="16:39:02.203294"/>
    <Point X="81.0" Y="145.0" T="16:39:02.203325"/>
    <Point X="80.0" Y="146.0" T="16:39:02.203356"/>
    <Point X="80.0" Y="150.0" T="16:39:02.203386"/>
    <Point X="80.0" Y="155.0" T="16:39:02.203416"/>
    <Point X="80.0" Y="160.0" T="16:39:02.203446"/>
    <Point X="79.0" Y="166.0" T="16:39:02.203476"/>
    <Point X="78.0" Y="175.0" T="16:39:02.203506"/>
    <Point X="77.0" Y="191.0" T="16:39:02.203628"/>
    <Point X="77.0" Y="211.0" T="16:39:02.203659"/>
    <Point X="76.0" Y="230.0" T="16:39:02.203689"/>
    <Point X="76.0" Y="246.0" T="16:39:02.203718"/>
    <Point X="76.0" Y="255.0" T="16:39:02.203748"/>
    <Point X="77.0" Y="273.0" T="16:39:02.203778"/>
    <Point X="78.0" Y="280.0" T="16:39:02.203808"/>
    <Point X="81.0" Y="292.0" T="16:39:02.203837"/>
    <Point X="82.0" Y="297.0" T="16:39:02.203867"/>
    <Point X="82.0" Y="300.0" T="16:39:02.203896"/>
    <Point X="83.0" Y="302.0" T="16:39:02.203925"/>
    <Point X="83.0" Y="304.0" T="16:39:02.203954"/>
    <Point X="84.0" Y="308.0" T="16:39:02.203984"/>
    <Point X="84.0" Y="309.0" T="16:39:02.204013"/>
    <Point X="85.0" Y="309.0" T="16:39:02.204042"/>
    <Point X="85.0" Y="310.0" T="16:39:02.204071"/>
    <Point X="86.0" Y="310.0" T="16:39:02.204100"/>
    <Point X="87.0" Y="310.0" T="16:39:02.204130"/>
    <Point X="89.0" Y="311.0" T="16:39:02.204160"/>
    <Point X="97.0" Y="311.0" T="16:39:02.204190"/>
    <Point X="102.0" Y="311.0" T="16:39:02.204218"/>
    <Point X="118.0" Y="312.0" T="16:39:02.204248"/>
    <Point X="127.0" Y="313.0" T="16:39:02.204277"/>
    <Point X="141.0" Y="314.0" T="16:39:02.204307"/>
    <Point X="163.0" Y="316.0" T="16:39:02.204336"/>
    <Point X="191.0" Y="317.0" T="16:39:02.204368"/>
    <Point X="219.0" Y="317.0" T="16:39:02.204407"/>
    <Point X="243.0" Y="317.0" T="16:39:02.204437"/>
    <Point X="266.0" Y="317.0" T="16:39:02.204467"/>
    <Point X="270.0" Y="317.0" T="16:39:02.204497"/>
    <Point X="279.0" Y="317.0" T="16:39:02.204527"/>
    <Point X="288.0" Y="317.0" T="16:39:02.204556"/>
    <Point X="299.0" Y="317.0" T="16:39:02.204586"/>
    <Point X="311.0" Y="315.0" T="16:39:02.204616"/>
    <Point X="326.0" Y="311.0" T="16:39:02.204646"/>
    <Point X="334.0" Y="310.0" T="16:39:02.204675"/>
    <Point X="348.0" Y="310.0" T="16:39:02.204705"/>
    <Point X="349.0" Y="310.0" T="16:39:02.204734"/>
    <Point X="349.0" Y="308.0" T="16:39:02.204764"/>
    <Point X="350.0" Y="304.0" T="16:39:02.204793"/>
    <Point X="351.0" Y="303.0" T="16:39:02.204822"/>
    <Point X="354.0" Y="299.0" T="16:39:02.204852"/>
    <Point X="356.0" Y="295.0" T="16:39:02.204881"/>
    <Point X="356.0" Y="293.0" T="16:39:02.204911"/>
    <Point X="356.0" Y="282.0" T="16:39:02.204940"/>
    <Point X="356.0" Y="278.0" T="16:39:02.204970"/>
    <Point X="354.0" Y="267.0" T="16:39:02.204999"/>
    <Point X="354.0" Y="258.0" T="16:39:02.205029"/>
    <Point X="354.0" Y="248.0" T="16:39:02.205058"/>
    <Point X="354.0" Y="234.0" T="16:39:02.205087"/>
    <Point X="352.0" Y="220.0" T="16:39:02.205117"/>
    <Point X="351.0" Y="207.0" T="16:39:02.205147"/>
    <Point X="351.0" Y="191.0" T="16:39:02.205177"/>
    <Point X="351.0" Y="188.0" T="16:39:02.205273"/>
    <Point X="351.0" Y="181.0" T="16:39:02.205304"/>
    <Point X="350.0" Y="175.0" T="16:39:02.205334"/>
    <Point X="349.0" Y="171.0" T="16:39:02.205363"/>
    <Point X="347.0" Y="168.0" T="16:39:02.205393"/>
    <Point X="346.0" Y="164.0" T="16:39:02.205422"/>
    <Point X="345.0" Y="161.0" T="16:39:02.205451"/>
    <Point X="345.0" Y="160.0" T="16:39:02.205480"/>
    <Point X="344.0" Y="160.0" T="16:39:02.205509"/>
    <Point X="343.0" Y="159.0" T="16:39:02.205538"/>
    <Point X="342.0" Y="159.0" T="16:39:02.205569"/>
    <Point X="337.0" Y="156.0" T="16:39:02.205605"/>
    <Point X="335.0" Y="154.0" T="16:39:02.205635"/>
    <Point X="332.0" Y="154.0" T="16:39:02.205664"/>
    <Point X="331.0" Y="153.0" T="16:39:02.205693"/>
    <Point X="330.0" Y="153.0" T="16:39:02.205723"/>
    <Point X="328.0" Y="152.0" T="16:39:02.205753"/>
    <Point X="325.0" Y="151.0" T="16:39:02.205782"/>
    <Point X="322.0" Y="151.0" T="16:39:02.205811"/>
    <Point X="319.0" Y="150.0" T="16:39:02.205840"/>
    <Point X="316.0" Y="150.0" T="16:39:02.205870"/>
    <Point X="310.0" Y="150.0" T="16:39:02.205899"/>
    <Point X="302.0" Y="150.0" T="16:39:02.205928"/>
    <Point X="286.0" Y="150.0" T="16:39:02.205957"/>
    <Point X="276.0" Y="150.0" T="16:39:02.205986"/>
    <Point X="267.0" Y="150.0" T="16:39:02.206015"/>
    <Point X="261.0" Y="150.0" T="16:39:02.206044"/>
    <Point X="238.0" Y="151.0" T="16:39:02.206073"/>
    <Point X="214.0" Y="152.0" T="16:39:02.206102"/>
    <Point X="206.0" Y="153.0" T="16:39:02.206132"/>
    <Point X="197.0" Y="153.0" T="16:39:02.206160"/>
    <Point X="184.0" Y="154.0" T="16:39:02.206189"/>
    <Point X="179.0" Y="154.0" T="16:39:02.206218"/>
    <Point X="166.0" Y="154.0" T="16:39:02.206247"/>
    <Point X="160.0" Y="154.0" T="16:39:02.206276"/>
    <Point X="154.0" Y="153.0" T="16:39:02.206306"/>
    <Point X="148.0" Y="153.0" T="16:39:02.206335"/>
    <Point X="142.0" Y="152.0" T="16:39:02.206365"/>
    <Point X="137.0" Y="151.0" T="16:39:02.206393"/>
    <Point X="133.0" Y="151.0" T="16:39:02.206422"/>
    <Point X="127.0" Y="150.0" T="16:39:02.206451"/>
    <Point X="119.0" Y="149.0" T="16:39:02.206480"/>
    <Point X="112.0" Y="148.0" T="16:39:02.206510"/>
    <Point X="108.0" Y="147.0" T="16:39:02.206539"/>
    <Point X="106.0" Y="147.0" T="16:39:02.206568"/>
  </Gesture>
