<?xml version="1.0" ?>
  <Gesture Name="check05" Subject="Anna G" Speed="medium" Number="5" NumPts="30" AppName="dollarstore-notepad" Date="2022-02-17" Time="15:04:51.013285">
    <Point X="210.0" Y="247.0" T="15:04:51.013338"/>
    <Point X="210.0" Y="249.0" T="15:04:51.013380"/>
    <Point X="210.0" Y="252.0" T="15:04:51.013420"/>
    <Point X="210.0" Y="253.0" T="15:04:51.013459"/>
    <Point X="210.0" Y="255.0" T="15:04:51.013497"/>
    <Point X="210.0" Y="260.0" T="15:04:51.013535"/>
    <Point X="210.0" Y="265.0" T="15:04:51.013572"/>
    <Point X="210.0" Y="268.0" T="15:04:51.013610"/>
    <Point X="210.0" Y="270.0" T="15:04:51.013649"/>
    <Point X="210.0" Y="271.0" T="15:04:51.013688"/>
    <Point X="210.0" Y="272.0" T="15:04:51.013726"/>
    <Point X="210.0" Y="273.0" T="15:04:51.013766"/>
    <Point X="211.0" Y="274.0" T="15:04:51.013812"/>
    <Point X="212.0" Y="274.0" T="15:04:51.013850"/>
    <Point X="212.0" Y="275.0" T="15:04:51.013888"/>
    <Point X="213.0" Y="275.0" T="15:04:51.013925"/>
    <Point X="213.0" Y="274.0" T="15:04:51.013963"/>
    <Point X="214.0" Y="271.0" T="15:04:51.014003"/>
    <Point X="216.0" Y="267.0" T="15:04:51.014043"/>
    <Point X="222.0" Y="258.0" T="15:04:51.014082"/>
    <Point X="231.0" Y="248.0" T="15:04:51.014121"/>
    <Point X="238.0" Y="239.0" T="15:04:51.014159"/>
    <Point X="249.0" Y="227.0" T="15:04:51.014195"/>
    <Point X="258.0" Y="218.0" T="15:04:51.014232"/>
    <Point X="264.0" Y="211.0" T="15:04:51.014269"/>
    <Point X="268.0" Y="207.0" T="15:04:51.014307"/>
    <Point X="271.0" Y="204.0" T="15:04:51.014344"/>
    <Point X="273.0" Y="202.0" T="15:04:51.014381"/>
    <Point X="274.0" Y="201.0" T="15:04:51.014420"/>
    <Point X="275.0" Y="201.0" T="15:04:51.014458"/>
  </Gesture>
